dyspatch/__init__.py
dyspatch-0.0.1.dist-info/METADATA
dyspatch-0.0.1.dist-info/WHEEL
dyspatch-0.0.1.dist-info/top_level.txt
dyspatch-0.0.1.dist-info/RECORD
