Metadata-Version: 2.1
Name: dyspatch
Version: 0.0.1
Summary: A simple events handler package.
Home-page: https://github.com/nerdguyahmad/dyspatch
Author: NerdGuyAhmad
License: MIT
Project-URL: Issue tracker, https://github.com/nerdguyahmad/dyspatch/issues
Platform: UNKNOWN
Classifier: Development Status :: 5 - Production/Stable
Classifier: License :: OSI Approved :: MIT License
Classifier: Intended Audience :: Developers
Classifier: Natural Language :: English
Classifier: Operating System :: OS Independent
Classifier: Programming Language :: Python :: 3.8
Classifier: Programming Language :: Python :: 3.9
Classifier: Topic :: Internet
Classifier: Topic :: Software Development :: Libraries
Classifier: Topic :: Software Development :: Libraries :: Python Modules
Classifier: Topic :: Utilities
Classifier: Typing :: Typed
Requires-Python: >=3.8.0
